README.md
setup.cfg
setup.py
mordred_web.egg-info/PKG-INFO
mordred_web.egg-info/SOURCES.txt
mordred_web.egg-info/dependency_links.txt
mordred_web.egg-info/requires.txt
mordred_web.egg-info/top_level.txt
python/mordred_web/__init__.py
python/mordred_web/__main__.py
python/mordred_web/db.py
python/mordred_web/exitable.py
python/mordred_web/task_queue.py
python/mordred_web/handler/__init__.py
python/mordred_web/handler/app.py
python/mordred_web/handler/calc.py
python/mordred_web/handler/common.py
python/mordred_web/handler/descriptor.py
python/mordred_web/handler/file.py
python/mordred_web/handler/singlefile.py
python/mordred_web/static/index.html
python/mordred_web/static/css/main.css
python/mordred_web/static/examples/example.sdf
python/mordred_web/static/examples/example.smi
python/mordred_web/static/fonts/FontAwesome.otf
python/mordred_web/static/fonts/fontawesome-webfont.eot
python/mordred_web/static/fonts/fontawesome-webfont.svg
python/mordred_web/static/fonts/fontawesome-webfont.ttf
python/mordred_web/static/fonts/fontawesome-webfont.woff
python/mordred_web/static/fonts/fontawesome-webfont.woff2
python/mordred_web/static/js/main.js