Metadata-Version: 1.0
Name: mordred-web
Version: 0.3.4
Summary: molecular descriptor calculator web UI
Home-page: https://github.com/mordred-descriptor/mordred-web
Author: Hirotomo Moriwaki
Author-email: philopon.dependence@gmail.com
License: BSD3
Keywords: QSAR chemoinformatics
Platform: any
